[
  {
    "theme": "power_tools",
    "post_count": 91,
    "avg_engagement": 140.12087912087912,
    "avg_relevance": 13.945934065934065,
    "total_comments": 3685,
    "demand_strength": 177824.60527472527,
    "sample_posts": [
      {
        "subreddit": "Makita",
        "title": "First time drill owner. What do you guys think about this Makita M8103KX2B set?",
        "selftext": "I was checking out a Bosch GSB 600 set and made a post on r/Tools earlier. Then stumbled upon this set for the Makita M8100KX2B which is cheaper (the Bosch set was $60 but $35 for just the drill, this one is $50 without the option to get just the drill) and the Makita seems to operate at a higher wattage at 710W compared to the Bosch's 600W (I understand that my intuition could be wrong on this).\n\nCurrently I just need to drill a few holes to mount a shelf at my first place so I figured it's time I got into power tools.\n\nEdit: I made a mistake in the title. The correct model is M8100KX2B, not M8103KX2B.",
        "score": 15,
        "num_comments": 18,
        "created_utc": 1774286065.0,
        "url": "https://i.redd.it/7hiub4hiutqg1.png",
        "permalink": "https://reddit.com/r/Makita/comments/1s1n141/first_time_drill_owner_what_do_you_guys_think/",
        "relevance_score": 39.35999999999999,
        "matched_brands": [
          "makita",
          "makita",
          "bosch",
          "ge",
          "bosch"
        ],
        "matched_products": [
          "drill"
        ],
        "matched_keywords": [],
        "detected_intents": [
          "learning_intent",
          "comparison"
        ]
      },
      {
        "subreddit": "Makita",
        "title": "New GPH03 Drill replace GPH01?",
        "selftext": "I plan to get the new GPH03/4AH high output battery bundle (considering Acmes bundle that comes with the high torque GDT04 impact driver and 2ag battery combo for just $100 more)\n\nIs there any reason to keep the GPH01 around aside from redundancy? Unlike the larger impact wrenches and drivers (like the GDT04 in that kit) It\u2019s only marginally larger/heavier, would there ever be a reason to reach for the GPH01 instead?\n\nWould it be worth holding on to either way? Are there times having multiple with different drill bits pre loaded is usefull for someone who isn\u2019t a contractor?",
        "score": 3,
        "num_comments": 10,
        "created_utc": 1774540554.0,
        "url": "https://www.reddit.com/r/Makita/comments/1s4bf71/new_gph03_drill_replace_gph01/",
        "permalink": "https://reddit.com/r/Makita/comments/1s4bf71/new_gph03_drill_replace_gph01/",
        "relevance_score": 37.44,
        "matched_brands": [
          "ge"
        ],
        "matched_products": [
          "drill",
          "impact driver"
        ],
        "matched_keywords": [
          "battery",
          "ah",
          "torque",
          "contractor"
        ],
        "detected_intents": [
          "buying_intent"
        ]
      },
      {
        "subreddit": "Makita",
        "title": "XSL02Z saw fence not aligned",
        "selftext": "I guess this is a fairly common problem with these saws. I bought this saw a couple years ago on Amazon and never registered it was really busy and the saw never seemed to be accurate so I just never used it and kept pulling out my huge 12 inch dewalt miter saw instead. I\u2019m finally looking closely at it and realize the fence is not aligned at all and it gets worse the higher up you go. What do you guys recommend I do? Order a replacement fence for about 30-40$ or try and fix this one somehow? ",
        "score": 5,
        "num_comments": 11,
        "created_utc": 1774574431.0,
        "url": "https://www.reddit.com/gallery/1s4q6yh",
        "permalink": "https://reddit.com/r/Makita/comments/1s4q6yh/xsl02z_saw_fence_not_aligned/",
        "relevance_score": 32.4,
        "matched_brands": [
          "dewalt",
          "dewalt",
          "ge"
        ],
        "matched_products": [
          "miter saw"
        ],
        "matched_keywords": [],
        "detected_intents": [
          "buying_intent",
          "troubleshooting",
          "troubleshooting"
        ]
      }
    ],
    "content_angle": "Power Tool Reviews & Professional Tips",
    "example_videos": [
      "Best cordless drills 2024",
      "Miter saw buying guide",
      "Tool storage solutions"
    ],
    "hashtags": [
      "#powertools",
      "#cordlesstools",
      "#dewalt",
      "#milwaukee",
      "#contractor"
    ]
  },
  {
    "theme": "buying_advice",
    "post_count": 49,
    "avg_engagement": 65.14285714285714,
    "avg_relevance": 26.851836734693876,
    "total_comments": 2813,
    "demand_strength": 85711.06285714285,
    "sample_posts": [
      {
        "subreddit": "appliances",
        "title": "Best Dishwasher UNDER $800 (Max ~$1000 w/ Install & Delivery)",
        "selftext": "My 11 year old Frigidaire took a crap, and now I am in the market for a new dishwasher. I do not plan to stay in my current house for more than another 5 years, for this was my starter home, and I am tired of not having a yard / having my walls shared with neighbors.\n\nHowever, every post I keep coming across repeats the same suggestions - Miele & Bosch. Miele & Bosch. Miele & Bosch.\n\nUnfortunately, neither of these brands makes a dishwasher within my price range (minus the Bosch 100 series, which everyone seems to warn against).\n\nI know to stay away from Samsung, Frigidaire, and LG, but every other recommendation comes with such mix reviews.\n\nI was looking at the Whirlpool **WDTA50SAKZ**, and thought I had made a good choice, but now I am second guessing myself.\n\nEdit: I ended up not going with a Bosch, for several reasons. \n\n1. All of the reviews seemed to make notes of the lack of drying features in the 100 - 500 series. I don\u2019t want to have to dry my dishes by hand. I\u2019m an attorney ",
        "score": 13,
        "num_comments": 85,
        "created_utc": 1774384730.0,
        "url": "https://www.reddit.com/r/Appliances/comments/1s2ppti/best_dishwasher_under_800_max_1000_w_install/",
        "permalink": "https://reddit.com/r/Appliances/comments/1s2ppti/best_dishwasher_under_800_max_1000_w_install/",
        "relevance_score": 73.8,
        "matched_brands": [
          "bosch",
          "whirlpool",
          "ge",
          "samsung",
          "lg",
          "frigidaire",
          "bosch",
          "miele"
        ],
        "matched_products": [
          "washer",
          "dishwasher"
        ],
        "matched_keywords": [],
        "detected_intents": [
          "buying_intent",
          "buying_intent",
          "buying_intent",
          "troubleshooting",
          "learning_intent"
        ]
      },
      {
        "subreddit": "appliances",
        "title": "Need a new Washing Machine, Speed Queens are too expensive and small. (US, $800 budget)",
        "selftext": "I know everyone is going to say Speed Queen first thing, but that's really not viable for me. They cost 2-3 times the other models I am looking at, while having a much smaller capacity. I could barely fit my blanket in my current washer, and it is much bigger.  \n \nAnyway I have a LG WT7100CW, it's an impeller washer with a 4.5Cu capacity, and the start button no longer responds. The power button and every other button and knob works, but the button to actually START a wash is not responding at all anymore (I hate capacitive buttons on appliances). Trying to look up replacement parts, nearly every part is $300, half of what we paid for the entire thing back in 2020, LG also wants $300 just to look at it. Trying to Google and YouTube information on trying to fix it was fruitless, and pretty much every test or service mode on the stupid thing requires pressing... the start button.  \n \nSo we figured enough is enough, we're going to replace it with a new one. We live in the US and max we ar",
        "score": 12,
        "num_comments": 47,
        "created_utc": 1774334315.0,
        "url": "https://www.reddit.com/r/Appliances/comments/1s26aov/need_a_new_washing_machine_speed_queens_are_too/",
        "permalink": "https://reddit.com/r/Appliances/comments/1s26aov/need_a_new_washing_machine_speed_queens_are_too/",
        "relevance_score": 66.11999999999999,
        "matched_brands": [
          "whirlpool",
          "ge",
          "lg",
          "speed queen"
        ],
        "matched_products": [
          "washing machine",
          "washer"
        ],
        "matched_keywords": [
          "capacity",
          "front load",
          "top load"
        ],
        "detected_intents": [
          "buying_intent",
          "buying_intent",
          "buying_intent",
          "buying_intent",
          "troubleshooting",
          "comparison",
          "comparison",
          "maintenance",
          "maintenance"
        ]
      },
      {
        "subreddit": "appliances",
        "title": "LG Canada Refrigerator Compressor Warranty Experience",
        "selftext": "I recently had a fridge stop cooling and information was fairly scattered, so I thought I\u2019d share here for others.  For context this happened in March 2026 in the Greater Toronto Area.\n\n**Issue**:  Fridge abruptly stopped cooling in under 6 years, which based on research is likely a failure of the linear compressor.\n\n**Troubleshooting**: Ran smart diagnostics on the app, cleaned the coils, and ran tests from the board.  No errors shown, which is apparently common with a compressor failure.\n\n**Warranty Summary:**  1 year full coverage, 7 years sealed system parts only (basically the cooling system), 10 years compressor parts only\n\n**Flat Rate Repair:**  $500+tax through LG.  This theoretically will get the fridge fixed with no additional surprise fees.  I filled in the form, got a list of available service providers, googled reviews to pick the best one, then scheduled for 2 days away.\n\n**Service Scheduling:**  Got a call from the service company the morning after submitting the form, a",
        "score": 10,
        "num_comments": 12,
        "created_utc": 1774290188.0,
        "url": "https://www.reddit.com/r/Appliances/comments/1s1p0ef/lg_canada_refrigerator_compressor_warranty/",
        "permalink": "https://reddit.com/r/Appliances/comments/1s1p0ef/lg_canada_refrigerator_compressor_warranty/",
        "relevance_score": 52.8,
        "matched_brands": [
          "bosch",
          "ge",
          "lg",
          "bosch"
        ],
        "matched_products": [
          "refrigerator",
          "fridge"
        ],
        "matched_keywords": [],
        "detected_intents": [
          "buying_intent",
          "troubleshooting",
          "troubleshooting",
          "troubleshooting",
          "troubleshooting",
          "maintenance",
          "maintenance"
        ]
      }
    ],
    "content_angle": "Product Buying Guides & Recommendations",
    "example_videos": [
      "What to look for when buying...",
      "Best value tools under $200",
      "Professional vs homeowner grade"
    ],
    "hashtags": [
      "#buyingguide",
      "#recommendations",
      "#bestvalue",
      "#professional"
    ]
  },
  {
    "theme": "how_to_guides",
    "post_count": 46,
    "avg_engagement": 73.58695652173913,
    "avg_relevance": 23.850434782608684,
    "total_comments": 1482,
    "demand_strength": 80733.7217391304,
    "sample_posts": [
      {
        "subreddit": "appliances",
        "title": "Best Dishwasher UNDER $800 (Max ~$1000 w/ Install & Delivery)",
        "selftext": "My 11 year old Frigidaire took a crap, and now I am in the market for a new dishwasher. I do not plan to stay in my current house for more than another 5 years, for this was my starter home, and I am tired of not having a yard / having my walls shared with neighbors.\n\nHowever, every post I keep coming across repeats the same suggestions - Miele & Bosch. Miele & Bosch. Miele & Bosch.\n\nUnfortunately, neither of these brands makes a dishwasher within my price range (minus the Bosch 100 series, which everyone seems to warn against).\n\nI know to stay away from Samsung, Frigidaire, and LG, but every other recommendation comes with such mix reviews.\n\nI was looking at the Whirlpool **WDTA50SAKZ**, and thought I had made a good choice, but now I am second guessing myself.\n\nEdit: I ended up not going with a Bosch, for several reasons. \n\n1. All of the reviews seemed to make notes of the lack of drying features in the 100 - 500 series. I don\u2019t want to have to dry my dishes by hand. I\u2019m an attorney ",
        "score": 13,
        "num_comments": 85,
        "created_utc": 1774384730.0,
        "url": "https://www.reddit.com/r/Appliances/comments/1s2ppti/best_dishwasher_under_800_max_1000_w_install/",
        "permalink": "https://reddit.com/r/Appliances/comments/1s2ppti/best_dishwasher_under_800_max_1000_w_install/",
        "relevance_score": 73.8,
        "matched_brands": [
          "bosch",
          "whirlpool",
          "ge",
          "samsung",
          "lg",
          "frigidaire",
          "bosch",
          "miele"
        ],
        "matched_products": [
          "washer",
          "dishwasher"
        ],
        "matched_keywords": [],
        "detected_intents": [
          "buying_intent",
          "buying_intent",
          "buying_intent",
          "troubleshooting",
          "learning_intent"
        ]
      },
      {
        "subreddit": "Chainsaw",
        "title": "New \"medium\" saw.",
        "selftext": "new to the forum but not new to chainsaws.\n\nI am a homeowner, I don't have much property or many trees, but I do have a wife that likes to burn in the fire pit outside.  \n\nI currently own a Stihl MS290, 20\" bar chisel chain & ported muffler, an Echo cs271t, 12\" bar ported muffler, will probably have a 10\" bar soon, and a Pole saw attachment for my Troy Bilt weed eater. The pole saw and the Echo work great for trimming the trees around the house and in my small orchard.  \n\nI've had the MS290 Farm Boss for 20 years. I'll probably have it until it dies, at which point it will likely recieve an MS390 big bore kit. I am, however,  getting older. A motorcycle accident and a diagnosis of a rare type of arthritis isn't helping my back or my hands much, and those 2 or 3 days a year that I go cut a load of wood make for a rough time wielding the MS290 all day.\n\nI think I need an in-between saw, and why not ask Reddit. Probably an 18\" bar, although not opposed to a 16\". I want light weight, high ",
        "score": 6,
        "num_comments": 48,
        "created_utc": 1774273198.0,
        "url": "https://www.reddit.com/r/Chainsaw/comments/1s1h5t9/new_medium_saw/",
        "permalink": "https://reddit.com/r/Chainsaw/comments/1s1h5t9/new_medium_saw/",
        "relevance_score": 56.16,
        "matched_brands": [
          "stihl",
          "echo",
          "poulan",
          "ge"
        ],
        "matched_products": [
          "chainsaw",
          "weed eater",
          "pole saw"
        ],
        "matched_keywords": [
          "professional grade"
        ],
        "detected_intents": [
          "learning_intent"
        ]
      },
      {
        "subreddit": "appliances",
        "title": "So this happened\u2026now looking for a new washer and dryer set.",
        "selftext": "Bought a Samsung washer and dryer set 11 years ago, and aside from a couple small repairs i did on the dryer, they have been reliable.  One day before leaving on vacation, my wife may or may not have overloaded the washer with sheets and towels\u2026drum liner pulled loose, sheets got tangled and the motor started burning (glad we were home and another reminder not to run a load and leave!).  I have done a fair bit of research, read reviews on suppliers sites, read many Reddit posts, checked YouTube, etc., and like many others I have found that I have no idea what to get.  I\u2019m looking for a mid priced set, focus on cleaning, general ease of use, and hopefully reliability.  I have learned that we got lucky getting 11 years out of our Samsung and it may not be the best brand to buy again.  Couple notes to help hopefully steer us in the right direction with recommendations:\n\nWe are on well water so water efficiency less important, though while our water is treated (iron remover, filters, softe",
        "score": 103,
        "num_comments": 132,
        "created_utc": 1774562874.0,
        "url": "https://i.redd.it/rlwsymfiqgrg1.jpeg",
        "permalink": "https://reddit.com/r/Appliances/comments/1s4ligk/so_this_happenednow_looking_for_a_new_washer_and/",
        "relevance_score": 52.199999999999996,
        "matched_brands": [
          "ge",
          "samsung",
          "lg",
          "speed queen"
        ],
        "matched_products": [
          "washer",
          "dryer"
        ],
        "matched_keywords": [
          "reliability"
        ],
        "detected_intents": [
          "buying_intent",
          "buying_intent",
          "troubleshooting",
          "learning_intent",
          "maintenance",
          "maintenance"
        ]
      }
    ],
    "content_angle": "How To Guides Content",
    "example_videos": [
      "Custom content needed"
    ],
    "hashtags": [
      "#how_to_guides"
    ]
  },
  {
    "theme": "major_appliances",
    "post_count": 69,
    "avg_engagement": 53.55072463768116,
    "avg_relevance": 21.24898550724636,
    "total_comments": 2683,
    "demand_strength": 78515.0014492753,
    "sample_posts": [
      {
        "subreddit": "appliances",
        "title": "Best Dishwasher UNDER $800 (Max ~$1000 w/ Install & Delivery)",
        "selftext": "My 11 year old Frigidaire took a crap, and now I am in the market for a new dishwasher. I do not plan to stay in my current house for more than another 5 years, for this was my starter home, and I am tired of not having a yard / having my walls shared with neighbors.\n\nHowever, every post I keep coming across repeats the same suggestions - Miele & Bosch. Miele & Bosch. Miele & Bosch.\n\nUnfortunately, neither of these brands makes a dishwasher within my price range (minus the Bosch 100 series, which everyone seems to warn against).\n\nI know to stay away from Samsung, Frigidaire, and LG, but every other recommendation comes with such mix reviews.\n\nI was looking at the Whirlpool **WDTA50SAKZ**, and thought I had made a good choice, but now I am second guessing myself.\n\nEdit: I ended up not going with a Bosch, for several reasons. \n\n1. All of the reviews seemed to make notes of the lack of drying features in the 100 - 500 series. I don\u2019t want to have to dry my dishes by hand. I\u2019m an attorney ",
        "score": 13,
        "num_comments": 85,
        "created_utc": 1774384730.0,
        "url": "https://www.reddit.com/r/Appliances/comments/1s2ppti/best_dishwasher_under_800_max_1000_w_install/",
        "permalink": "https://reddit.com/r/Appliances/comments/1s2ppti/best_dishwasher_under_800_max_1000_w_install/",
        "relevance_score": 73.8,
        "matched_brands": [
          "bosch",
          "whirlpool",
          "ge",
          "samsung",
          "lg",
          "frigidaire",
          "bosch",
          "miele"
        ],
        "matched_products": [
          "washer",
          "dishwasher"
        ],
        "matched_keywords": [],
        "detected_intents": [
          "buying_intent",
          "buying_intent",
          "buying_intent",
          "troubleshooting",
          "learning_intent"
        ]
      },
      {
        "subreddit": "appliances",
        "title": "Need a new Washing Machine, Speed Queens are too expensive and small. (US, $800 budget)",
        "selftext": "I know everyone is going to say Speed Queen first thing, but that's really not viable for me. They cost 2-3 times the other models I am looking at, while having a much smaller capacity. I could barely fit my blanket in my current washer, and it is much bigger.  \n \nAnyway I have a LG WT7100CW, it's an impeller washer with a 4.5Cu capacity, and the start button no longer responds. The power button and every other button and knob works, but the button to actually START a wash is not responding at all anymore (I hate capacitive buttons on appliances). Trying to look up replacement parts, nearly every part is $300, half of what we paid for the entire thing back in 2020, LG also wants $300 just to look at it. Trying to Google and YouTube information on trying to fix it was fruitless, and pretty much every test or service mode on the stupid thing requires pressing... the start button.  \n \nSo we figured enough is enough, we're going to replace it with a new one. We live in the US and max we ar",
        "score": 12,
        "num_comments": 47,
        "created_utc": 1774334315.0,
        "url": "https://www.reddit.com/r/Appliances/comments/1s26aov/need_a_new_washing_machine_speed_queens_are_too/",
        "permalink": "https://reddit.com/r/Appliances/comments/1s26aov/need_a_new_washing_machine_speed_queens_are_too/",
        "relevance_score": 66.11999999999999,
        "matched_brands": [
          "whirlpool",
          "ge",
          "lg",
          "speed queen"
        ],
        "matched_products": [
          "washing machine",
          "washer"
        ],
        "matched_keywords": [
          "capacity",
          "front load",
          "top load"
        ],
        "detected_intents": [
          "buying_intent",
          "buying_intent",
          "buying_intent",
          "buying_intent",
          "troubleshooting",
          "comparison",
          "comparison",
          "maintenance",
          "maintenance"
        ]
      },
      {
        "subreddit": "appliances",
        "title": "Besides Bosch and Miele, who makes a good dishwasher?",
        "selftext": "I know Bosch and Miele are the reddit go-to answers, along with avoiding Samsung and LG.   What's the word on GE, Maytag, whirlpool, Frigidaire,armana, sharp, etc?",
        "score": 32,
        "num_comments": 139,
        "created_utc": 1774479620.0,
        "url": "https://www.reddit.com/r/Appliances/comments/1s3qcpb/besides_bosch_and_miele_who_makes_a_good/",
        "permalink": "https://reddit.com/r/Appliances/comments/1s3qcpb/besides_bosch_and_miele_who_makes_a_good/",
        "relevance_score": 63.599999999999994,
        "matched_brands": [
          "bosch",
          "whirlpool",
          "ge",
          "samsung",
          "lg",
          "frigidaire",
          "maytag",
          "bosch",
          "miele"
        ],
        "matched_products": [
          "washer",
          "dishwasher"
        ],
        "matched_keywords": [],
        "detected_intents": []
      }
    ],
    "content_angle": "Appliance Buying Guides & Maintenance",
    "example_videos": [
      "Washer and dryer buying guide",
      "HVAC maintenance tips",
      "Refrigerator troubleshooting"
    ],
    "hashtags": [
      "#appliances",
      "#HVAC",
      "#homeappliances",
      "#maintenance"
    ]
  },
  {
    "theme": "product_comparisons",
    "post_count": 29,
    "avg_engagement": 67.89655172413794,
    "avg_relevance": 26.482344827586203,
    "total_comments": 777,
    "demand_strength": 52143.736965517244,
    "sample_posts": [
      {
        "subreddit": "appliances",
        "title": "Need a new Washing Machine, Speed Queens are too expensive and small. (US, $800 budget)",
        "selftext": "I know everyone is going to say Speed Queen first thing, but that's really not viable for me. They cost 2-3 times the other models I am looking at, while having a much smaller capacity. I could barely fit my blanket in my current washer, and it is much bigger.  \n \nAnyway I have a LG WT7100CW, it's an impeller washer with a 4.5Cu capacity, and the start button no longer responds. The power button and every other button and knob works, but the button to actually START a wash is not responding at all anymore (I hate capacitive buttons on appliances). Trying to look up replacement parts, nearly every part is $300, half of what we paid for the entire thing back in 2020, LG also wants $300 just to look at it. Trying to Google and YouTube information on trying to fix it was fruitless, and pretty much every test or service mode on the stupid thing requires pressing... the start button.  \n \nSo we figured enough is enough, we're going to replace it with a new one. We live in the US and max we ar",
        "score": 12,
        "num_comments": 47,
        "created_utc": 1774334315.0,
        "url": "https://www.reddit.com/r/Appliances/comments/1s26aov/need_a_new_washing_machine_speed_queens_are_too/",
        "permalink": "https://reddit.com/r/Appliances/comments/1s26aov/need_a_new_washing_machine_speed_queens_are_too/",
        "relevance_score": 66.11999999999999,
        "matched_brands": [
          "whirlpool",
          "ge",
          "lg",
          "speed queen"
        ],
        "matched_products": [
          "washing machine",
          "washer"
        ],
        "matched_keywords": [
          "capacity",
          "front load",
          "top load"
        ],
        "detected_intents": [
          "buying_intent",
          "buying_intent",
          "buying_intent",
          "buying_intent",
          "troubleshooting",
          "comparison",
          "comparison",
          "maintenance",
          "maintenance"
        ]
      },
      {
        "subreddit": "Makita",
        "title": "Talk to me about rotary hammers...",
        "selftext": "I'm considering a rotary hammer purchase. I'm a lowly home DIY user. However, I live in a region where timber-frame buildings are overwhelmingly the norm. I've only ever had to drill into masonry once, and I then found out there was trick I wasn't aware of that avoided the need to do so entirely.\n\nMy immediate usage will be chipping up \\~55 sq ft of 12\\*12 floor tile, and then it will see recurring use to break up extremely heavy clay/rocky soil. Do I actually want a demolition hammer and not a rotary hammer? Makita's demolition hammers are all SDS-MAX, with a price tag to match. I find it hard to believe I need such a beast for my use and, honestly, if I do, it will likely be better for me to rent. \n\n  \nWill an SDS+ hammer do what I need? Doesn't have to be the fastest since I'm not doing this professionally...\n\nI'm not currently on the XGT platform, but maybe this and a leaf blower is what gets me to take the leap... Also fine to stay with 36V, or even 18V if the only trade-off is re",
        "score": 5,
        "num_comments": 9,
        "created_utc": 1774285578.0,
        "url": "https://www.reddit.com/r/Makita/comments/1s1msc2/talk_to_me_about_rotary_hammers/",
        "permalink": "https://reddit.com/r/Makita/comments/1s1msc2/talk_to_me_about_rotary_hammers/",
        "relevance_score": 59.74799999999999,
        "matched_brands": [
          "makita",
          "makita",
          "ge"
        ],
        "matched_products": [
          "leaf blower",
          "drill",
          "rotary hammer",
          "multitool"
        ],
        "matched_keywords": [
          "battery",
          "trade"
        ],
        "detected_intents": [
          "comparison",
          "maintenance"
        ]
      },
      {
        "subreddit": "appliances",
        "title": "Purchasing Advice",
        "selftext": "My husband and I just bought our first home. We're working on fixing the inside first, so we have a few months before we start buying new appliances. I wanted to do some research in that time. \n\nI've heard stories of people who spend thousands on a new fridge just to have it display ads while they're getting water. My sister just bought a new washer and dryer that she can start from an app on her phone. And all I can think of, is how are these machines gonna function when one of the hundreds of electrical features malfunctions? \n\nI want something simple. Something that's not gonna break right away. Something that we can buy spare parts for. I don't need something old necessarily, I just need a decent product. \n\nWe're buying a range stove, dishwasher, microwave, refrigerator, and a washer and dryer. Does anyone know what brands are reputable? Or a certain type of machine that functions better than fancier versions? ",
        "score": 7,
        "num_comments": 14,
        "created_utc": 1774221095.0,
        "url": "https://www.reddit.com/r/Appliances/comments/1s10e7h/purchasing_advice/",
        "permalink": "https://reddit.com/r/Appliances/comments/1s10e7h/purchasing_advice/",
        "relevance_score": 47.76,
        "matched_brands": [
          "ge"
        ],
        "matched_products": [
          "washer",
          "dryer",
          "refrigerator",
          "fridge",
          "dishwasher"
        ],
        "matched_keywords": [],
        "detected_intents": [
          "buying_intent",
          "buying_intent",
          "troubleshooting",
          "troubleshooting",
          "learning_intent",
          "comparison"
        ]
      }
    ],
    "content_angle": "Product Comparisons Content",
    "example_videos": [
      "Custom content needed"
    ],
    "hashtags": [
      "#product_comparisons"
    ]
  },
  {
    "theme": "repair_help",
    "post_count": 42,
    "avg_engagement": 42.30952380952381,
    "avg_relevance": 25.59571428571428,
    "total_comments": 1404,
    "demand_strength": 45483.58428571428,
    "sample_posts": [
      {
        "subreddit": "appliances",
        "title": "Best Dishwasher UNDER $800 (Max ~$1000 w/ Install & Delivery)",
        "selftext": "My 11 year old Frigidaire took a crap, and now I am in the market for a new dishwasher. I do not plan to stay in my current house for more than another 5 years, for this was my starter home, and I am tired of not having a yard / having my walls shared with neighbors.\n\nHowever, every post I keep coming across repeats the same suggestions - Miele & Bosch. Miele & Bosch. Miele & Bosch.\n\nUnfortunately, neither of these brands makes a dishwasher within my price range (minus the Bosch 100 series, which everyone seems to warn against).\n\nI know to stay away from Samsung, Frigidaire, and LG, but every other recommendation comes with such mix reviews.\n\nI was looking at the Whirlpool **WDTA50SAKZ**, and thought I had made a good choice, but now I am second guessing myself.\n\nEdit: I ended up not going with a Bosch, for several reasons. \n\n1. All of the reviews seemed to make notes of the lack of drying features in the 100 - 500 series. I don\u2019t want to have to dry my dishes by hand. I\u2019m an attorney ",
        "score": 13,
        "num_comments": 85,
        "created_utc": 1774384730.0,
        "url": "https://www.reddit.com/r/Appliances/comments/1s2ppti/best_dishwasher_under_800_max_1000_w_install/",
        "permalink": "https://reddit.com/r/Appliances/comments/1s2ppti/best_dishwasher_under_800_max_1000_w_install/",
        "relevance_score": 73.8,
        "matched_brands": [
          "bosch",
          "whirlpool",
          "ge",
          "samsung",
          "lg",
          "frigidaire",
          "bosch",
          "miele"
        ],
        "matched_products": [
          "washer",
          "dishwasher"
        ],
        "matched_keywords": [],
        "detected_intents": [
          "buying_intent",
          "buying_intent",
          "buying_intent",
          "troubleshooting",
          "learning_intent"
        ]
      },
      {
        "subreddit": "appliances",
        "title": "Need a new Washing Machine, Speed Queens are too expensive and small. (US, $800 budget)",
        "selftext": "I know everyone is going to say Speed Queen first thing, but that's really not viable for me. They cost 2-3 times the other models I am looking at, while having a much smaller capacity. I could barely fit my blanket in my current washer, and it is much bigger.  \n \nAnyway I have a LG WT7100CW, it's an impeller washer with a 4.5Cu capacity, and the start button no longer responds. The power button and every other button and knob works, but the button to actually START a wash is not responding at all anymore (I hate capacitive buttons on appliances). Trying to look up replacement parts, nearly every part is $300, half of what we paid for the entire thing back in 2020, LG also wants $300 just to look at it. Trying to Google and YouTube information on trying to fix it was fruitless, and pretty much every test or service mode on the stupid thing requires pressing... the start button.  \n \nSo we figured enough is enough, we're going to replace it with a new one. We live in the US and max we ar",
        "score": 12,
        "num_comments": 47,
        "created_utc": 1774334315.0,
        "url": "https://www.reddit.com/r/Appliances/comments/1s26aov/need_a_new_washing_machine_speed_queens_are_too/",
        "permalink": "https://reddit.com/r/Appliances/comments/1s26aov/need_a_new_washing_machine_speed_queens_are_too/",
        "relevance_score": 66.11999999999999,
        "matched_brands": [
          "whirlpool",
          "ge",
          "lg",
          "speed queen"
        ],
        "matched_products": [
          "washing machine",
          "washer"
        ],
        "matched_keywords": [
          "capacity",
          "front load",
          "top load"
        ],
        "detected_intents": [
          "buying_intent",
          "buying_intent",
          "buying_intent",
          "buying_intent",
          "troubleshooting",
          "comparison",
          "comparison",
          "maintenance",
          "maintenance"
        ]
      },
      {
        "subreddit": "appliances",
        "title": "LG Canada Refrigerator Compressor Warranty Experience",
        "selftext": "I recently had a fridge stop cooling and information was fairly scattered, so I thought I\u2019d share here for others.  For context this happened in March 2026 in the Greater Toronto Area.\n\n**Issue**:  Fridge abruptly stopped cooling in under 6 years, which based on research is likely a failure of the linear compressor.\n\n**Troubleshooting**: Ran smart diagnostics on the app, cleaned the coils, and ran tests from the board.  No errors shown, which is apparently common with a compressor failure.\n\n**Warranty Summary:**  1 year full coverage, 7 years sealed system parts only (basically the cooling system), 10 years compressor parts only\n\n**Flat Rate Repair:**  $500+tax through LG.  This theoretically will get the fridge fixed with no additional surprise fees.  I filled in the form, got a list of available service providers, googled reviews to pick the best one, then scheduled for 2 days away.\n\n**Service Scheduling:**  Got a call from the service company the morning after submitting the form, a",
        "score": 10,
        "num_comments": 12,
        "created_utc": 1774290188.0,
        "url": "https://www.reddit.com/r/Appliances/comments/1s1p0ef/lg_canada_refrigerator_compressor_warranty/",
        "permalink": "https://reddit.com/r/Appliances/comments/1s1p0ef/lg_canada_refrigerator_compressor_warranty/",
        "relevance_score": 52.8,
        "matched_brands": [
          "bosch",
          "ge",
          "lg",
          "bosch"
        ],
        "matched_products": [
          "refrigerator",
          "fridge"
        ],
        "matched_keywords": [],
        "detected_intents": [
          "buying_intent",
          "troubleshooting",
          "troubleshooting",
          "troubleshooting",
          "troubleshooting",
          "maintenance",
          "maintenance"
        ]
      }
    ],
    "content_angle": "Troubleshooting & Repair Tutorials",
    "example_videos": [
      "Common tool problems and fixes",
      "Appliance troubleshooting guide",
      "When to repair vs replace"
    ],
    "hashtags": [
      "#repair",
      "#troubleshooting",
      "#DIYrepair",
      "#maintenance"
    ]
  },
  {
    "theme": "outdoor_power_equipment",
    "post_count": 44,
    "avg_engagement": 15.340909090909092,
    "avg_relevance": 22.035181818181815,
    "total_comments": 1316,
    "demand_strength": 14873.747727272725,
    "sample_posts": [
      {
        "subreddit": "Makita",
        "title": "Talk to me about rotary hammers...",
        "selftext": "I'm considering a rotary hammer purchase. I'm a lowly home DIY user. However, I live in a region where timber-frame buildings are overwhelmingly the norm. I've only ever had to drill into masonry once, and I then found out there was trick I wasn't aware of that avoided the need to do so entirely.\n\nMy immediate usage will be chipping up \\~55 sq ft of 12\\*12 floor tile, and then it will see recurring use to break up extremely heavy clay/rocky soil. Do I actually want a demolition hammer and not a rotary hammer? Makita's demolition hammers are all SDS-MAX, with a price tag to match. I find it hard to believe I need such a beast for my use and, honestly, if I do, it will likely be better for me to rent. \n\n  \nWill an SDS+ hammer do what I need? Doesn't have to be the fastest since I'm not doing this professionally...\n\nI'm not currently on the XGT platform, but maybe this and a leaf blower is what gets me to take the leap... Also fine to stay with 36V, or even 18V if the only trade-off is re",
        "score": 5,
        "num_comments": 9,
        "created_utc": 1774285578.0,
        "url": "https://www.reddit.com/r/Makita/comments/1s1msc2/talk_to_me_about_rotary_hammers/",
        "permalink": "https://reddit.com/r/Makita/comments/1s1msc2/talk_to_me_about_rotary_hammers/",
        "relevance_score": 59.74799999999999,
        "matched_brands": [
          "makita",
          "makita",
          "ge"
        ],
        "matched_products": [
          "leaf blower",
          "drill",
          "rotary hammer",
          "multitool"
        ],
        "matched_keywords": [
          "battery",
          "trade"
        ],
        "detected_intents": [
          "comparison",
          "maintenance"
        ]
      },
      {
        "subreddit": "Chainsaw",
        "title": "New \"medium\" saw.",
        "selftext": "new to the forum but not new to chainsaws.\n\nI am a homeowner, I don't have much property or many trees, but I do have a wife that likes to burn in the fire pit outside.  \n\nI currently own a Stihl MS290, 20\" bar chisel chain & ported muffler, an Echo cs271t, 12\" bar ported muffler, will probably have a 10\" bar soon, and a Pole saw attachment for my Troy Bilt weed eater. The pole saw and the Echo work great for trimming the trees around the house and in my small orchard.  \n\nI've had the MS290 Farm Boss for 20 years. I'll probably have it until it dies, at which point it will likely recieve an MS390 big bore kit. I am, however,  getting older. A motorcycle accident and a diagnosis of a rare type of arthritis isn't helping my back or my hands much, and those 2 or 3 days a year that I go cut a load of wood make for a rough time wielding the MS290 all day.\n\nI think I need an in-between saw, and why not ask Reddit. Probably an 18\" bar, although not opposed to a 16\". I want light weight, high ",
        "score": 6,
        "num_comments": 48,
        "created_utc": 1774273198.0,
        "url": "https://www.reddit.com/r/Chainsaw/comments/1s1h5t9/new_medium_saw/",
        "permalink": "https://reddit.com/r/Chainsaw/comments/1s1h5t9/new_medium_saw/",
        "relevance_score": 56.16,
        "matched_brands": [
          "stihl",
          "echo",
          "poulan",
          "ge"
        ],
        "matched_products": [
          "chainsaw",
          "weed eater",
          "pole saw"
        ],
        "matched_keywords": [
          "professional grade"
        ],
        "detected_intents": [
          "learning_intent"
        ]
      },
      {
        "subreddit": "Ryobi",
        "title": "Hard choice - Used 48v ZTR480 zero turn vs new 80v Z3 Zero Turn",
        "selftext": "Hey all! Sorry if this is the wrong sub, LONG time Ryobi fan (got my first One+ tools way back in 2004 and have a massive collection of 18v and 40v tools now).\n\nI need to buy a mower for my land and torn between two routes:\n\n**Option 1 - Used 48v ZTR480ex**\n\nI've been watching the used market for nearly a year now and have learned a lot about the 48v first-gen zero turns.  The new lithium batteries on the market make this a serious contender.  Problem is I'd be looking to spend around $2000 for the mower used (hopefully less than 50 hours run time from what I've been seeing on most of them), then I'd need to spend $600+ on a lithium battery.  \n\nI'd love to find something lower than $1500, but that just doesn't exist locally, anytime I see anything close to $1500 it gets snatched up in a day (and even then I've only seen it happen two or three times over the past year).  \n\nFactor in the lack of warranty and I'm concerned about lifespan before something major fails like a control board o",
        "score": 2,
        "num_comments": 3,
        "created_utc": 1774476681.0,
        "url": "https://www.reddit.com/r/ryobi/comments/1s3p31w/hard_choice_used_48v_ztr480_zero_turn_vs_new_80v/",
        "permalink": "https://reddit.com/r/ryobi/comments/1s3p31w/hard_choice_used_48v_ztr480_zero_turn_vs_new_80v/",
        "relevance_score": 44.51999999999999,
        "matched_brands": [
          "ryobi",
          "ryobi",
          "ge"
        ],
        "matched_products": [
          "zero turn"
        ],
        "matched_keywords": [
          "battery"
        ],
        "detected_intents": [
          "buying_intent",
          "buying_intent",
          "troubleshooting",
          "learning_intent",
          "learning_intent",
          "comparison",
          "comparison"
        ]
      }
    ],
    "content_angle": "OPE Reviews, Maintenance & Buying Guides",
    "example_videos": [
      "Chainsaw buying guide 2024",
      "Pressure washer comparison",
      "Lawn mower maintenance tips"
    ],
    "hashtags": [
      "#chainsaw",
      "#lawnmower",
      "#pressurewasher",
      "#OPE",
      "#yardwork"
    ]
  },
  {
    "theme": "utility_appliances",
    "post_count": 9,
    "avg_engagement": 41.77777777777778,
    "avg_relevance": 12.424444444444443,
    "total_comments": 253,
    "demand_strength": 4671.591111111111,
    "sample_posts": [
      {
        "subreddit": "BuyItForLife",
        "title": "Finally bought a proper vacuum",
        "selftext": "5 years ago I bought a Bissell at Walmart for $70 and it worked fine in apartments and rental homes but I figured being a homeowner also meant it was time to get a real vacuum. And apparently this Sebo E3 premium is the one of the better ones available.\n\nSo far it lives up to the hype. There is a bit of a learning curve transitioning from an upright to a canister, but after a couple of months I will never go back to an upright. I love how quick I can pop off the power head and use a dusting attachment for corners. And the built in extension is something I never knew I needed. No more extension wand attachments.\n\nAnd the consumables aren't crazy overpriced either. Bags/filters/brushes all seem pretty reasonable to buy, and I've been seeing them go on sale frequently.\n\nTwo (albeit minor) complaints  \n  \n1. The hose occasionally gets twisted up during use, and you can untwist it on the handle because it has built in slip rings for the power head. If the hose attachment on the canister had",
        "score": 141,
        "num_comments": 27,
        "created_utc": 1774559266.0,
        "url": "https://i.redd.it/cda9cldyagrg1.jpeg",
        "permalink": "https://reddit.com/r/BuyItForLife/comments/1s4jy57/finally_bought_a_proper_vacuum/",
        "relevance_score": 23.16,
        "matched_brands": [
          "ge"
        ],
        "matched_products": [
          "vacuum"
        ],
        "matched_keywords": [],
        "detected_intents": [
          "buying_intent",
          "learning_intent",
          "learning_intent",
          "comparison",
          "maintenance"
        ]
      },
      {
        "subreddit": "HomeImprovement",
        "title": "Can anyone recommend the best cleaning tools for daily use that really save time",
        "selftext": "I\u2019ve been trying to figure out how people keep their homes tidy every day without spending hours cleaning. Mops and vacuums feel like they barely scratch the surface. I live in a moderately sized apartment with a dog, so there\u2019s always hair and dirt showing up in the most random places.\n\nI\u2019m curious about tools that are easy to use, lightweight, and actually motivate you to clean more often. Something that doesn\u2019t feel like a workout every time you just want to pick up a bit of mess. What\u2019s your holy grail for keeping things manageable day-to-day?\n\nAlso, if there\u2019s anything that makes it fun or oddly satisfying to clean, please share your tips, sometimes I need that little extra push to actually use the tools instead of letting clutter pile up.",
        "score": 28,
        "num_comments": 45,
        "created_utc": 1774577264.0,
        "url": "https://www.reddit.com/r/HomeImprovement/comments/1s4r9hx/can_anyone_recommend_the_best_cleaning_tools_for/",
        "permalink": "https://reddit.com/r/HomeImprovement/comments/1s4r9hx/can_anyone_recommend_the_best_cleaning_tools_for/",
        "relevance_score": 20.76,
        "matched_brands": [
          "ge"
        ],
        "matched_products": [
          "vacuum"
        ],
        "matched_keywords": [],
        "detected_intents": [
          "buying_intent",
          "learning_intent",
          "comparison",
          "maintenance"
        ]
      },
      {
        "subreddit": "Carpentry",
        "title": "Dust Extractors",
        "selftext": "Nz Builder wanting to buy a m class vacuum for work. $1000/$1200 is pretty much it. \n\nAny other recommendations or suggestions?\n\nIs it true that L class vacuums pretty much the same as M class? Heard that before- heard the \u201cwasting your money\u201d part too just buy a cheap vac from the local. Need some help cheers \ud83e\udef6\ud83c\udffe",
        "score": 20,
        "num_comments": 33,
        "created_utc": 1774429751.0,
        "url": "https://www.reddit.com/gallery/1s35mt0",
        "permalink": "https://reddit.com/r/Carpentry/comments/1s35mt0/dust_extractors/",
        "relevance_score": 14.399999999999999,
        "matched_brands": [
          "ge"
        ],
        "matched_products": [
          "vacuum"
        ],
        "matched_keywords": [],
        "detected_intents": [
          "buying_intent"
        ]
      }
    ],
    "content_angle": "Home Utility Equipment Reviews",
    "example_videos": [
      "Best shop vacuums 2024",
      "Air purifier comparison",
      "Dehumidifier buying guide"
    ],
    "hashtags": [
      "#shopvac",
      "#airpurifier",
      "#homeimprovement",
      "#utility"
    ]
  }
]