[
  {
    "theme": "general",
    "post_count": 58,
    "avg_engagement": 382.32758620689657,
    "total_comments": 3448,
    "demand_strength": 22175.0,
    "sample_posts": [
      {
        "subreddit": "Tools",
        "title": "How many people own some Ryobi tools even if they aren't your main tools?",
        "selftext": "Just wondering if anyone uses some Ryobi stuff in addition to your \"main\" brand of tools? And if you do, what Ryobi tools do you use?\n\nI mainly use Makita and some of the Milwaukee M12, but Ryobi really rocks for their fans, nail guns to supplement my pneumatic ones, and I actually really like their cordless angle grinders for the price.",
        "score": 113,
        "num_comments": 274,
        "created_utc": 1758496897.0,
        "url": "https://www.reddit.com/r/Tools/comments/1nn6u0f/how_many_people_own_some_ryobi_tools_even_if_they/",
        "permalink": "https://reddit.com/r/Tools/comments/1nn6u0f/how_many_people_own_some_ryobi_tools_even_if_they/",
        "demand_signals": [],
        "matched_keywords": [
          "angle grinder",
          "nail gun",
          "cordless"
        ]
      },
      {
        "subreddit": "Dewalt",
        "title": "DCN21pl not sinking",
        "selftext": "Worked great with no issues for building a shed and few other things. Sat in storage for a year and now it won’t drive nails all the way. Full battery. Any ideas?",
        "score": 505,
        "num_comments": 133,
        "created_utc": 1758287338.0,
        "url": "https://v.redd.it/1he3drbze4qf1",
        "permalink": "https://reddit.com/r/Dewalt/comments/1nl34ne/dcn21pl_not_sinking/",
        "demand_signals": [],
        "matched_keywords": [
          "battery"
        ]
      },
      {
        "subreddit": "Dewalt",
        "title": "What's the difference between this battery and the ones not xr",
        "selftext": "They're both DCB205. ",
        "score": 69,
        "num_comments": 60,
        "created_utc": 1758589823.0,
        "url": "https://i.redd.it/7lpvpwifetqf1.png",
        "permalink": "https://reddit.com/r/Dewalt/comments/1no4472/whats_the_difference_between_this_battery_and_the/",
        "demand_signals": [],
        "matched_keywords": [
          "battery"
        ]
      }
    ],
    "content_angle": "General Content",
    "example_videos": [
      "Custom content needed"
    ],
    "hashtags": [
      "#general"
    ],
    "matched_videos": [
      {
        "video_id": "oZf0u6HXqkE",
        "title": "Milwaukee Cordless Grinder Repair - Replacing the Guard (Milwaukee Part # 14-32-0210)",
        "channel": "fixtechguides",
        "description_snippet": "Do you need a replacement Guard Assembly for your Grinder? eReplacementParts.com has thousands of replacement parts for a variety of Power Tools, Outdoor Power Equipment, and Appliances. To...",
        "relevance_score": 18,
        "match_reasons": [
          "Brand match: milwaukee",
          "Product match: grinder",
          "Fuzzy Reddit keyword: angle grinder (76.92307692307692)",
          "Reddit keyword: cordless",
          "Heavy repair focus (penalty)"
        ]
      },
      {
        "video_id": "nOychPGimN4",
        "title": "Hammer Drill Repair - Replacing the Battery Terminal (Makita Part # 643852-2)",
        "channel": "fixtechguides",
        "description_snippet": "http://www.ereplacementparts.com/terminal-p-719473.html Click here for more information on this part, installation instructions and more.\n\nThis particular battery terminal is specific to Makita...",
        "relevance_score": 14,
        "match_reasons": [
          "Brand match: makita",
          "Product match: battery",
          "Reddit keyword: battery",
          "Heavy repair focus (penalty)"
        ]
      },
      {
        "video_id": "meFXCaWystw",
        "title": "How to Replace the Switch on a Makita Grinder--A Quick Fix",
        "channel": "fixtechguides",
        "description_snippet": "In this Quick Fix, Mark guides you through the steps needed to replace a broken switch in a Makita grinder. Switches fail, but lukcily, replacing them is fast and easy. And this video shows...",
        "relevance_score": 14,
        "match_reasons": [
          "Brand match: makita",
          "Product match: grinder"
        ]
      }
    ]
  },
  {
    "theme": "beginner_guidance",
    "post_count": 17,
    "avg_engagement": 556.1176470588235,
    "total_comments": 2589,
    "demand_strength": 9454.0,
    "sample_posts": [
      {
        "subreddit": "Tools",
        "title": "Is this a normal amount of oil from an oil-lubricated air compressor?",
        "selftext": "I've just bought a new compressor and oil is coming through the duster. \n\nMy current setup is:\n\nCompressor > inline filter ---10m---> filter/regulator ---10m coil---> blower (running at 2 bar).\n\n  \nIt seems like a lot, especially since the blower will be my main tool of use. What does everyone think? and how much oil should I be getting?",
        "score": 325,
        "num_comments": 95,
        "created_utc": 1758753026.0,
        "url": "https://v.redd.it/jjg22h4cv6rf1",
        "permalink": "https://reddit.com/r/Tools/comments/1npq3xr/is_this_a_normal_amount_of_oil_from_an/",
        "demand_signals": [],
        "matched_keywords": [
          "air compressor"
        ]
      },
      {
        "subreddit": "Dewalt",
        "title": "two separate batteries. two separate chargers. pretty much brand new. two different circuts. 15 amp flexvolts",
        "selftext": "bought these guys and had them sitting on the charger over night in the shed. had the window open, woke up to that sweet smell of lithium this morning. these are the dcb615s, I contacted dewalt and they told me I have to ship them at my expense to a service center to determine if I'm able to recieve replacements or not. pretty sure that even my dumbest ideas can't top how dumb it is to ship fried 15 amp lithium batteries through the mail. \n\nSo no, I'm not shipping them out. not really sure what ",
        "score": 414,
        "num_comments": 96,
        "created_utc": 1758580336.0,
        "url": "https://i.redd.it/elaugn08msqf1.jpeg",
        "permalink": "https://reddit.com/r/Dewalt/comments/1no0ozo/two_separate_batteries_two_separate_chargers/",
        "demand_signals": [],
        "matched_keywords": [
          "miter saw"
        ]
      },
      {
        "subreddit": "Dewalt",
        "title": "NTD",
        "selftext": "Finally got my fan (battery not included). I've been looking at it for a while now and decided to get it after working alot of hours after starting a new job.",
        "score": 204,
        "num_comments": 75,
        "created_utc": 1758484730.0,
        "url": "https://i.redd.it/e2im08nxpkqf1.jpeg",
        "permalink": "https://reddit.com/r/Dewalt/comments/1nn1yko/ntd/",
        "demand_signals": [],
        "matched_keywords": [
          "battery"
        ]
      }
    ],
    "content_angle": "Tool & Equipment Education for Beginners",
    "example_videos": [
      "Tools every homeowner needs",
      "Beginner tool buying guide"
    ],
    "hashtags": [
      "#beginnertools",
      "#DIYbeginner",
      "#homeimprovement",
      "#tools101"
    ],
    "matched_videos": [
      {
        "video_id": "PZkZniNQmb0",
        "title": "How to Replace the Blade on a Miter Saw--A Quick Fix",
        "channel": "fixtechguides",
        "description_snippet": "In this Quick Fix Tutorial, Mark guides you through the steps needed to replace a miter saw blade. With a little help from Mark and OEM parts from eReplacementParts.com you can complete this...",
        "relevance_score": 47,
        "match_reasons": [
          "Theme keyword: guide",
          "Theme keyword: tutorial",
          "Theme keyword: how to",
          "Product match: saw",
          "Reddit keyword: miter saw",
          "Content type: guide",
          "Content type: tutorial"
        ]
      },
      {
        "video_id": "_vShfKez9vo",
        "title": "How to Test a Small Engine for Spark",
        "channel": "fixtechguides",
        "description_snippet": "Testing for sparks refers to testing the engine's ignition coil and ensuring it is producing enough electricity to make a spark at the spark plug. This tutorial will guide you on how to perform...",
        "relevance_score": 44,
        "match_reasons": [
          "Theme keyword: guide",
          "Theme keyword: tutorial",
          "Theme keyword: how to",
          "Fuzzy theme keyword match: first time (70.0)",
          "Content type: guide",
          "Content type: tutorial"
        ]
      },
      {
        "video_id": "FkrnuS69AAQ",
        "title": "How to Service an Aprilaire Electronic Air Cleaner",
        "channel": "fixtechguides",
        "description_snippet": "Keep your breathing space cleaner and fresher by learning how to service your Aprilaire electronic air cleaner. By following this basic tutorial, you can learn simple maintenance tips, including...",
        "relevance_score": 43,
        "match_reasons": [
          "Theme keyword: tutorial",
          "Theme keyword: how to",
          "Theme keyword: basic",
          "Theme keyword: learn",
          "Content type: tutorial"
        ]
      }
    ]
  },
  {
    "theme": "kitchen_appliances",
    "post_count": 20,
    "avg_engagement": 436.5,
    "total_comments": 806,
    "demand_strength": 8730.0,
    "sample_posts": [
      {
        "subreddit": "Dewalt",
        "title": "Can someone help me, please?",
        "selftext": "Tried to jump my car, like I did before and it didn’t work. When I looked things up, it said it should at least 12.4, but this says 11. It’s charging right now. Should I let it charge to 12 (it’s going very slow now that it’s at 11.4). And try again, or is it, or my car battery cooked? It was making a clicking noise when I tried to use it to jump my car. Thanks for the help. ",
        "score": 13,
        "num_comments": 14,
        "created_utc": 1758422950.0,
        "url": "https://i.redd.it/j3zmiwy7mfqf1.jpeg",
        "permalink": "https://reddit.com/r/Dewalt/comments/1nmgtje/can_someone_help_me_please/",
        "demand_signals": [
          "can someone"
        ],
        "matched_keywords": [
          "battery"
        ]
      },
      {
        "subreddit": "Ryobi",
        "title": "Is this battery cooked?",
        "selftext": "Please photos, this battery will not charge! \nIs it cooked or is there a way to revive it.\nThe charger is good I can charge my 2 Ah battery.\n",
        "score": 4,
        "num_comments": 9,
        "created_utc": 1758303211.0,
        "url": "https://www.reddit.com/gallery/1nl9ztc",
        "permalink": "https://reddit.com/r/ryobi/comments/1nl9ztc/is_this_battery_cooked/",
        "demand_signals": [],
        "matched_keywords": [
          "battery"
        ]
      },
      {
        "subreddit": "woodworking",
        "title": "I made a knife for my son",
        "selftext": "I thought I’d share something I made for my son. He has been wanting to help with cooking more and more, and he always wants to use the kitchen knives. I made him this knife so he could practice knife skills in a way that he can’t hurt himself or anyone else. The blade is some kind of maple (I think) with a Brazilian walnut handle and padauk bolsters. I finished it with Howard’s butcher board conditioner so it will be safe to use on food.",
        "score": 1008,
        "num_comments": 47,
        "created_utc": 1758470477.0,
        "url": "https://www.reddit.com/gallery/1nmvry5",
        "permalink": "https://reddit.com/r/woodworking/comments/1nmvry5/i_made_a_knife_for_my_son/",
        "demand_signals": [
          "help with"
        ],
        "matched_keywords": [
          "blade"
        ]
      }
    ],
    "content_angle": "Appliance Reviews & Kitchen Hacks",
    "example_videos": [
      "Air fryer vs oven comparison",
      "Kitchen appliance buying guide"
    ],
    "hashtags": [
      "#kitchenappliances",
      "#airfryer",
      "#kitchenhacks",
      "#cooking"
    ],
    "matched_videos": [
      {
        "video_id": "UdXD4R2ECyE",
        "title": "How to Replace the Motor Capacitor on a KitchenAid Food Processor",
        "channel": "fixtechguides",
        "description_snippet": "Your food processor's capcitator serves as a battery that stores energy for your processor. This video will show you how to replace it, saving you time and money in the process. \n\nHelpful items...",
        "relevance_score": 29,
        "match_reasons": [
          "Fuzzy theme keyword match: toaster (71.42857142857143)",
          "Theme keyword: food processor",
          "Product match: battery",
          "Reddit keyword: battery"
        ]
      },
      {
        "video_id": "Smk3okUIZZc",
        "title": "How to Replace the Blade Guard Assembly on a DeWALT DW718 Miter Saw (Part # N353439)",
        "channel": "fixtechguides",
        "description_snippet": "Get a replacement blade guard assembly for your DeWALT DW718 miter saw here: http://www.ereplacementparts.com/lower-guard-assembly-p-91033.html\n\nThis tutorial will show you how to remove and...",
        "relevance_score": 27,
        "match_reasons": [
          "Fuzzy theme keyword match: oven (75.0)",
          "Fuzzy theme keyword match: mixer (80.0)",
          "Product match: blade",
          "Reddit keyword: blade"
        ]
      },
      {
        "video_id": "Ry2l-SceZ48",
        "title": "How to Replace the Line Limiter Blade on a Black and Decker CST1200 String Trimmer (Part# 243805-00)",
        "channel": "fixtechguides",
        "description_snippet": "Get a replacement line limiter blade for your Black and Decker CST1200 string trimmer here: http://www.ereplacementparts.com/blade-p-95888.html\n\nThis tutorial will show you how to remove and...",
        "relevance_score": 27,
        "match_reasons": [
          "Fuzzy theme keyword match: oven (75.0)",
          "Fuzzy theme keyword match: mixer (80.0)",
          "Product match: blade",
          "Reddit keyword: blade"
        ]
      }
    ]
  },
  {
    "theme": "cutting_tools",
    "post_count": 32,
    "avg_engagement": 160.625,
    "total_comments": 1831,
    "demand_strength": 5140.0,
    "sample_posts": [
      {
        "subreddit": "Tools",
        "title": "My complete loadout for fishing walls-  I retrofit without cutting Sheetrock.",
        "selftext": "Here are my tools-  everything has a purpose, and there are some things I had to invent myself. Everything you see here keeps me from having to cut Sheetrock. And there are NO blind drill shots, I have the $1k Bosch studfinder, and inspection cameras-  also I spend time searching for possible issues-  I inspect my top plate, bottom plate, other side of wall, attic and crawlspace before committing to a location.  YouTube channel coming soon. ",
        "score": 213,
        "num_comments": 82,
        "created_utc": 1758209938.0,
        "url": "https://i.redd.it/no0bon5s0ypf1.jpeg",
        "permalink": "https://reddit.com/r/Tools/comments/1nkbo3o/my_complete_loadout_for_fishing_walls_i_retrofit/",
        "demand_signals": [],
        "matched_keywords": [
          "drill"
        ]
      },
      {
        "subreddit": "Tools",
        "title": "Tips to remove this hellacious hex bolt? (Switching saw blades)",
        "selftext": "I'm struggling to remove the saw blade on my new, pretty cheap Metabo HPT miter saw. It's been a multiple-day ordeal, and even using a hammer on the hex bar hasn't helped at all (that was a last resort). \n\nThis is left-hand threaded, so it turns clockwise to remove. I'm turning it in the right direction. \n\nThanks!",
        "score": 171,
        "num_comments": 194,
        "created_utc": 1758571186.0,
        "url": "https://www.reddit.com/gallery/1nnwv8r",
        "permalink": "https://reddit.com/r/Tools/comments/1nnwv8r/tips_to_remove_this_hellacious_hex_bolt_switching/",
        "demand_signals": [
          "cheap"
        ],
        "matched_keywords": [
          "miter saw",
          "blade"
        ]
      },
      {
        "subreddit": "Dewalt",
        "title": "Saw spinning but blade not moving?",
        "selftext": "Had this saw for two years. A few days ago I attempted to make some 45° cuts with my circular saw on some 2x12s. I noticed that even though I was using a speed square the saw would force itself away from the cut once I got close to the end. So I tried to apply a bit more pressure to keep it against the speed square. I then noticed that the saw blade stopped spinning but I could still hear it \"running\". Happened twice so I decided not to push the issue. Is this something I need to send to a profe",
        "score": 26,
        "num_comments": 36,
        "created_utc": 1758415032.0,
        "url": "https://i.redd.it/zt3q4hpoyeqf1.jpeg",
        "permalink": "https://reddit.com/r/Dewalt/comments/1nme8l9/saw_spinning_but_blade_not_moving/",
        "demand_signals": [
          "stopped"
        ],
        "matched_keywords": [
          "circular saw",
          "blade"
        ]
      }
    ],
    "content_angle": "Chainsaw & Cutting Tool Reviews/Tips",
    "example_videos": [
      "Chainsaw maintenance in 60 seconds",
      "Best budget chainsaws 2024"
    ],
    "hashtags": [
      "#chainsaw",
      "#powertools",
      "#DIY",
      "#woodworking"
    ],
    "matched_videos": [
      {
        "video_id": "U6UzuCLoVog",
        "title": "CHAINSAW REPAIR: How to Replace the Chain on Your Chainsaw | FIX.com",
        "channel": "fixtechguides",
        "description_snippet": "Your chainsaw's chain is the cutting blade that allows the tool to cut materials. If the chain is damaged to the point that it can't be fixed, this video will show you how to replace the chain...",
        "relevance_score": 75,
        "match_reasons": [
          "Theme keyword: chainsaw",
          "Fuzzy theme keyword match: chain saw (94.11764705882352)",
          "Theme keyword: saw",
          "Theme keyword: cutting",
          "Theme keyword: blade",
          "Theme keyword: cut",
          "Product match: saw",
          "Product match: blade",
          "Reddit keyword: blade"
        ]
      },
      {
        "video_id": "AycxZLXvEgU",
        "title": "Tool Tear Down: Orbital Sander | How to Disassemble Your Orbital Sander | eReplacementParts.com",
        "channel": "fixtechguides",
        "description_snippet": "In previous videos we've taken apart a Reciprocating Saw, a Circular Saw, and a Cordless Drill, but today we're going to be taking a look at the disassembly process of an Orbital Sander. Most...",
        "relevance_score": 74,
        "match_reasons": [
          "Fuzzy theme keyword match: chain saw (77.77777777777779)",
          "Theme keyword: saw",
          "Fuzzy theme keyword match: cutting (71.42857142857143)",
          "Theme keyword: circular saw",
          "Theme keyword: reciprocating saw",
          "Product match: saw",
          "Product match: bit",
          "Product match: drill",
          "Reddit keyword: drill",
          "Reddit keyword: circular saw"
        ]
      },
      {
        "video_id": "iUBMViME_oY",
        "title": "How to Change the Blade Clamp on the Bosch RS15 and RS20 saws",
        "channel": "fixtechguides",
        "description_snippet": "Learn how to change the blade clamp on the Bosch RS15 and RS2 reciprocating saw with this helpful video from Dale, one of eReplacementParts.com's professional tool repair technicians.\n\nFor...",
        "relevance_score": 71,
        "match_reasons": [
          "Fuzzy theme keyword match: chain saw (77.77777777777779)",
          "Theme keyword: saw",
          "Fuzzy theme keyword match: cutting (71.42857142857143)",
          "Theme keyword: blade",
          "Theme keyword: reciprocating saw",
          "Brand match: bosch",
          "Product match: saw",
          "Product match: blade",
          "Reddit keyword: blade"
        ]
      }
    ]
  },
  {
    "theme": "cleaning_equipment",
    "post_count": 69,
    "avg_engagement": 37.768115942028984,
    "total_comments": 3475,
    "demand_strength": 2606.0,
    "sample_posts": [
      {
        "subreddit": "Ryobi",
        "title": "Ryobi Pressure Washer Recall - Model and Serial Number Location",
        "selftext": "TL;DR - This is how you find your pressure washer model and serial number. Ignore the red circle as this was from the Ryobi website where they show you incorrectly where to find your model number.\n\n**Longer Version - Ryobi, I hope you're listening.**\n\nI went to the Ryobi website to see if my pressure washer was on the recall list. They want your model number and serial number. The attached graphic is from their website and the red circle is where they tell you to look for the model number and th",
        "score": 7,
        "num_comments": 1,
        "created_utc": 1758407433.0,
        "url": "https://i.redd.it/4eatflf4beqf1.jpeg",
        "permalink": "https://reddit.com/r/ryobi/comments/1nmbjl8/ryobi_pressure_washer_recall_model_and_serial/",
        "demand_signals": [
          "how to",
          "how to"
        ],
        "matched_keywords": [
          "pressure washer"
        ]
      },
      {
        "subreddit": "Ryobi",
        "title": "40v string trimmer bump feed problems",
        "selftext": "I've got a 40v string trimmer using .08 line. I consistently have problems with tangles. If I can get 15 min without a tangle I'm happy. \n\nWhat am I doing wrong? I feel like there's enough pressure on the turning meechinism to keep the line taught but withing a few minutes one side or both get sucked into the head and I have to start over. \n\nIt's mostly for edge work against a brick house or a level concrete drive. ",
        "score": 2,
        "num_comments": 5,
        "created_utc": 1758483299.0,
        "url": "https://www.reddit.com/r/ryobi/comments/1nn1crl/40v_string_trimmer_bump_feed_problems/",
        "permalink": "https://reddit.com/r/ryobi/comments/1nn1crl/40v_string_trimmer_bump_feed_problems/",
        "demand_signals": [],
        "matched_keywords": [
          "string trimmer"
        ]
      },
      {
        "subreddit": "HomeImprovement",
        "title": "Which Pressure Washer Would You Buy With $300?",
        "selftext": "I’ve been setting aside a budget for a good pressure washer and wanted to get some input from folks here. If you had around $300 to spend, which pressure washer would you recommend for home use?\n\nI’m mostly looking at electric pressure washers since they’re easier to maintain for things like patios, cars, siding, and general around-the-house cleaning. But I’ve also seen people swear by gas models when you need extra power.\n\nWhat I’d love to hear is:\n\n* Which brands/models have lasted for you lon",
        "score": 46,
        "num_comments": 67,
        "created_utc": 1758487702.0,
        "url": "https://www.reddit.com/r/HomeImprovement/comments/1nn38bo/which_pressure_washer_would_you_buy_with_300/",
        "permalink": "https://reddit.com/r/HomeImprovement/comments/1nn38bo/which_pressure_washer_would_you_buy_with_300/",
        "demand_signals": [
          "recommend",
          "budget"
        ],
        "matched_keywords": [
          "pressure washer"
        ]
      }
    ],
    "content_angle": "Pressure Washing & Cleaning Equipment",
    "example_videos": [
      "Pressure washer setup guide",
      "Before/after cleaning reveals"
    ],
    "hashtags": [
      "#pressurewashing",
      "#cleaning",
      "#satisfying",
      "#powerwashing"
    ],
    "matched_videos": [
      {
        "video_id": "df-0PXlGHRE",
        "title": "Should I Wash In Hot Water Only? Find Out Which Washer Tips Work, and Which are Myths!",
        "channel": "partselect",
        "description_snippet": "Have you ever heard that you should wash your clothes in hot water only? Should you clean your washer every month? Does more detergent mean more cleaning power? We'll put these common washer...",
        "relevance_score": 67,
        "match_reasons": [
          "Fuzzy theme keyword match: power washer (75.0)",
          "Theme keyword: washer",
          "Theme keyword: cleaning",
          "Theme keyword: wash",
          "Theme keyword: clean",
          "Fuzzy theme keyword match: power wash (70.0)",
          "Fuzzy theme keyword match: hose (75.0)",
          "Content type: tips"
        ]
      },
      {
        "video_id": "cc_a2zc_hE0",
        "title": "WASHER REPAIR: Leaking Washer Troubleshooting - Vent | FIX.com",
        "channel": "fixtechguides",
        "description_snippet": "We've already looked at Hoses and Drain Cleanouts as potential spots for a Leak to occur in your Washer, but now it's time to look at your Vents. In this video, we'll show you how to troubleshoot...",
        "relevance_score": 64,
        "match_reasons": [
          "Fuzzy theme keyword match: power washer (75.0)",
          "Theme keyword: washer",
          "Fuzzy theme keyword match: cleaning (75.0)",
          "Theme keyword: wash",
          "Theme keyword: clean",
          "Fuzzy theme keyword match: power wash (70.0)",
          "Theme keyword: hose"
        ]
      },
      {
        "video_id": "wa2osyA_sWQ",
        "title": "WASHER REPAIR: How to Inspect, Remove, and Clean Water Pressure Tube | FIX.com",
        "channel": "fixtechguides",
        "description_snippet": "Your Washer has many tubes that transport water throughout the appliance when it is running, and the Water Pressure tube is one of the most important. It helps the Pressure Switch tell your...",
        "relevance_score": 62,
        "match_reasons": [
          "Fuzzy theme keyword match: pressure washer (73.33333333333334)",
          "Fuzzy theme keyword match: power washer (75.0)",
          "Theme keyword: washer",
          "Theme keyword: wash",
          "Theme keyword: clean",
          "Fuzzy theme keyword match: pressure wash (76.92307692307692)",
          "Fuzzy theme keyword match: power wash (70.0)"
        ]
      }
    ]
  },
  {
    "theme": "drilling_tools",
    "post_count": 31,
    "avg_engagement": 64.83870967741936,
    "total_comments": 1249,
    "demand_strength": 2010.0000000000002,
    "sample_posts": [
      {
        "subreddit": "Tools",
        "title": "Funny moment that made me appreciate my tools more",
        "selftext": "The other night I was sitting on my couch half distracted on my phone, when I glanced over at my little tool rack. It hit me how much easier life has gotten just from slowly building up a decent set. A couple years ago I didn’t even own a drill and every small repair felt like a massive headache. Now I’ve got a handful of solid basics a drill, socket set, level, and a few other essentials and it’s wild how much stress they’ve saved me. Instead of putting things off or improvising with the wrong ",
        "score": 219,
        "num_comments": 48,
        "created_utc": 1758713628.0,
        "url": "https://www.reddit.com/r/Tools/comments/1np9p8n/funny_moment_that_made_me_appreciate_my_tools_more/",
        "permalink": "https://reddit.com/r/Tools/comments/1np9p8n/funny_moment_that_made_me_appreciate_my_tools_more/",
        "demand_signals": [],
        "matched_keywords": [
          "drill"
        ]
      },
      {
        "subreddit": "Tools",
        "title": "Finally upgraded my drill after years of using a hand me down",
        "selftext": "I’ve been using my dad’s old corded drill for years. It still technically works, but the chuck slips and the cord is all frayed. I finally had some extra money saved from a win on rollingriches and grabbed a Milwaukee cordless set this week. Honestly, it feels like night and day lighter, faster, and no extension cords everywhere. I spent half the afternoon just finding excuses to use it.",
        "score": 197,
        "num_comments": 33,
        "created_utc": 1758631368.0,
        "url": "https://www.reddit.com/r/Tools/comments/1nogcch/finally_upgraded_my_drill_after_years_of_using_a/",
        "permalink": "https://reddit.com/r/Tools/comments/1nogcch/finally_upgraded_my_drill_after_years_of_using_a/",
        "demand_signals": [],
        "matched_keywords": [
          "drill",
          "cordless",
          "chuck"
        ]
      },
      {
        "subreddit": "Tools",
        "title": "Thank you dewalt grinder warranty",
        "selftext": "Bought a ton of dewalt XR stuff during November Black Friday sales last year, waited years to choose which brand while babying my 2007 dewalt kit.  (1/4 driver still going! Replacement batteries…)\n\nAnyway xr grinder was a big hit, $250 with a battery, but I used a $50 HD pro-extra perk.   It was bigger/heavier than my corded makitas, but was the only paddle switch model they had.\n\nGot used to it real quick.  Very handy with the speed control knob and no cord.\n\nWell it lasted til July 2025.  I us",
        "score": 106,
        "num_comments": 27,
        "created_utc": 1758378104.0,
        "url": "https://www.reddit.com/gallery/1nlzgyy",
        "permalink": "https://reddit.com/r/Tools/comments/1nlzgyy/thank_you_dewalt_grinder_warranty/",
        "demand_signals": [],
        "matched_keywords": [
          "battery"
        ]
      }
    ],
    "content_angle": "Drill & Driver Comparisons/Tutorials",
    "example_videos": [
      "Impact driver vs regular drill",
      "Drill bit guide for beginners"
    ],
    "hashtags": [
      "#drill",
      "#impactdriver",
      "#powertools",
      "#construction"
    ],
    "matched_videos": [
      {
        "video_id": "boehGcrozmE",
        "title": "Drill Repair - Removing a Stuck, Seized, Stripped or Stubborn Chuck (Makita LXPH01)",
        "channel": "fixtechguides",
        "description_snippet": "http://www.ereplacementparts.com/makita-lxph01z-18v-lxt-lithiumion-cordless-hammer-driverdrill-parts-c-97_16247_187891.html Click here for more information on this part, installation instructions...",
        "relevance_score": 71,
        "match_reasons": [
          "Theme keyword: drill",
          "Fuzzy theme keyword match: drilling (76.92307692307692)",
          "Fuzzy theme keyword match: hammer drill (75.0)",
          "Theme keyword: driver",
          "Fuzzy theme keyword match: drill bit (80.0)",
          "Product match: drill",
          "Product match: driver",
          "Reddit keyword: drill",
          "Reddit keyword: cordless",
          "Reddit keyword: chuck"
        ]
      },
      {
        "video_id": "zVlxGYYzV9Q",
        "title": "How to Replace the Brush Spring in a Milwaukee Cordless Drill",
        "channel": "fixtechguides",
        "description_snippet": "MORE DRILLING. LESS BILLING. If broken drills and service bills are boring holes in your budget, it's time to face the fix. This tutorial will show you how to easily, expertly and economically...",
        "relevance_score": 67,
        "match_reasons": [
          "Theme keyword: drill",
          "Theme keyword: drilling",
          "Theme keyword: boring",
          "Theme keyword: hole",
          "Brand match: milwaukee",
          "Product match: drill",
          "Reddit keyword: drill",
          "Reddit keyword: cordless",
          "Content type: tutorial"
        ]
      },
      {
        "video_id": "AUmqey7Lbx8",
        "title": "How to Replace the Brush Card in a Milwaukee Cordless Drill",
        "channel": "fixtechguides",
        "description_snippet": "MORE DRILLING. LESS BILLING. If broken drills and service bills are boring holes in your budget, it's time to face the fix. This tutorial will show you how to easily, expertly and economically...",
        "relevance_score": 67,
        "match_reasons": [
          "Theme keyword: drill",
          "Theme keyword: drilling",
          "Theme keyword: boring",
          "Theme keyword: hole",
          "Brand match: milwaukee",
          "Product match: drill",
          "Reddit keyword: drill",
          "Reddit keyword: cordless",
          "Content type: tutorial"
        ]
      }
    ]
  },
  {
    "theme": "repair_help",
    "post_count": 13,
    "avg_engagement": 88.61538461538461,
    "total_comments": 1270,
    "demand_strength": 1152.0,
    "sample_posts": [
      {
        "subreddit": "Dewalt",
        "title": "First ever Router, how did i do?",
        "selftext": "I bought it because Im building racks and cabinets in my construction trailer, hoping to start a side hustle building and fixing things.\nAny advice would be much appreciated.",
        "score": 16,
        "num_comments": 12,
        "created_utc": 1758256011.0,
        "url": "https://www.reddit.com/gallery/1nku00q",
        "permalink": "https://reddit.com/r/Dewalt/comments/1nku00q/first_ever_router_how_did_i_do/",
        "demand_signals": [
          "advice"
        ],
        "matched_keywords": [
          "router"
        ]
      },
      {
        "subreddit": "Makita",
        "title": "Makita LS0815FL – clicking noise from blade guard, any fix?",
        "selftext": "Hi! I’ve got a Makita LS0815FL that works fine overall, but when the blade guard is mounted it makes a distinct click about halfway down when lowering the arm. I already lubricated the return spring, which solved the squeaking, but this clicking remains.\n\nI’ve recorded a short video so you can hear it. Has anyone run into this before or know how to adjust/fix it?",
        "score": 9,
        "num_comments": 7,
        "created_utc": 1758364921.0,
        "url": "https://v.redd.it/lor0y0p8taqf1",
        "permalink": "https://reddit.com/r/Makita/comments/1nluwrt/makita_ls0815fl_clicking_noise_from_blade_guard/",
        "demand_signals": [
          "how to"
        ],
        "matched_keywords": [
          "blade"
        ]
      },
      {
        "subreddit": "Makita",
        "title": "Drt50 stopped working",
        "selftext": "I have a drt50 router, was working this morning , I turned of the machine to change bits and it wouldn't start anymore. Eventually brought it in for repair but did people have this issue also? I have it for less than a year and not abusing it. I do everything in multiple passes etc",
        "score": 1,
        "num_comments": 1,
        "created_utc": 1758553607.0,
        "url": "https://www.reddit.com/r/Makita/comments/1nnp0ui/drt50_stopped_working/",
        "permalink": "https://reddit.com/r/Makita/comments/1nnp0ui/drt50_stopped_working/",
        "demand_signals": [
          "stopped"
        ],
        "matched_keywords": [
          "router"
        ]
      }
    ],
    "content_angle": "DIY Repair Tutorials",
    "example_videos": [
      "Fix it yourself tutorials",
      "Common appliance problems"
    ],
    "hashtags": [
      "#DIYrepair",
      "#fixit",
      "#repair",
      "#maintenance"
    ],
    "matched_videos": [
      {
        "video_id": "0IBiGPmGNSw",
        "title": "Router Repair - Replacing Collet Components (Porter Cable 690 Series)",
        "channel": "fixtechguides",
        "description_snippet": "http://www.ereplacementparts.com/porter-cable-690-fixed-base-router-parts-c-129_1672_1940.html Click here for more information on this part, installation instructions and more.\n\nThese particular...",
        "relevance_score": 75,
        "match_reasons": [
          "Theme keyword: repair",
          "Theme keyword: fix",
          "Theme keyword: replace",
          "Theme keyword: replacement",
          "Theme keyword: part",
          "Fuzzy theme keyword match: service (71.42857142857143)",
          "Product match: router",
          "Reddit keyword: router",
          "Content type: repair",
          "Content type: fix"
        ]
      },
      {
        "video_id": "KHq4bWKbgG4",
        "title": "How to Replace the Brushes on a Porter Cable 7518 or 7519 Router--A Quick Fix (Part # 873P)",
        "channel": "fixtechguides",
        "description_snippet": "Mark is here to help you replace the brushes in your Porter Cable 7518 or 7519 router. This simple repair will breathe lots of new life back into your router, and can help troubleshoot problems...",
        "relevance_score": 75,
        "match_reasons": [
          "Theme keyword: repair",
          "Theme keyword: fix",
          "Theme keyword: troubleshoot",
          "Theme keyword: replace",
          "Fuzzy theme keyword match: replacement (72.72727272727273)",
          "Theme keyword: part",
          "Product match: router",
          "Reddit keyword: router",
          "Content type: repair",
          "Content type: fix"
        ]
      },
      {
        "video_id": "aem658ZRopQ",
        "title": "How to Replace the Brushes on a Porter Cable 690 Series Router--A Quick Fix",
        "channel": "fixtechguides",
        "description_snippet": "In this video, Mark shows you how to replace the brushes on a Porter Cable 690 series router. This simple repair can get your router running again, which means you can get back to your projects...",
        "relevance_score": 71,
        "match_reasons": [
          "Theme keyword: repair",
          "Theme keyword: fix",
          "Theme keyword: replace",
          "Fuzzy theme keyword match: replacement (72.72727272727273)",
          "Fuzzy theme keyword match: part (75.0)",
          "Fuzzy theme keyword match: service (71.42857142857143)",
          "Product match: router",
          "Reddit keyword: router",
          "Content type: repair",
          "Content type: fix"
        ]
      }
    ]
  },
  {
    "theme": "lawn_care",
    "post_count": 6,
    "avg_engagement": 32.5,
    "total_comments": 110,
    "demand_strength": 195.0,
    "sample_posts": [
      {
        "subreddit": "Ryobi",
        "title": "Can't get my blades off",
        "selftext": "I was trying to remove my blades on my mower and the nut unthreaded about 3 turns and then beared down.  Now the blades are loose but I cannot remove the nut or tighten it to secure the blades and there isn't enough of a gap to get my skinniest channel locks into to lock down the drive shaft.  Is there any other way to lock it so that I can remove the nut?",
        "score": 13,
        "num_comments": 15,
        "created_utc": 1758389122.0,
        "url": "https://v.redd.it/jq8k2numtcqf1",
        "permalink": "https://reddit.com/r/ryobi/comments/1nm43z5/cant_get_my_blades_off/",
        "demand_signals": [],
        "matched_keywords": [
          "blade"
        ]
      },
      {
        "subreddit": "Ryobi",
        "title": "Trying to get warranty repair on 40v mower",
        "selftext": "My 40v mower recently stopped spinning the blade. The powered movement still works so the battery and the safety bar are working. Just the blade is not spinning when I press the button to engage the blade. The nearest repair facility is 300 miles away. Ryobi support is telling me to ship the mower to the repair site. How am I supposed to find a box big enough to ship this back? This really is pushing me away from using Ryobi lawn equipment if they cannot support warranty repairs for customers in",
        "score": 3,
        "num_comments": 3,
        "created_utc": 1758725021.0,
        "url": "https://www.reddit.com/r/ryobi/comments/1npe0rk/trying_to_get_warranty_repair_on_40v_mower/",
        "permalink": "https://reddit.com/r/ryobi/comments/1npe0rk/trying_to_get_warranty_repair_on_40v_mower/",
        "demand_signals": [
          "stopped"
        ],
        "matched_keywords": [
          "battery",
          "blade"
        ]
      },
      {
        "subreddit": "Ryobi",
        "title": "Ride on mower battery dying, want to make sure I am getting the right replacement battery.",
        "selftext": "We have had this ride on mower for about five years now and the battery is finally giving out. I want to upgrade and this battery replacement is pitched as a lighter, longer lasting alternative but I’m not too savvy with this sort of thing. Will this battery be able to to hook up and replace the current original battery or am I looking at the wrong one? \n\nHere is the link to my mower RY48130: https://www.homedepot.com/p/RYOBI-48V-Brushless-30-in-50-Ah-Battery-Electric-Rear-Engine-Riding-Mower-RY",
        "score": 2,
        "num_comments": 6,
        "created_utc": 1758636609.0,
        "url": "https://www.reddit.com/gallery/1noifs6",
        "permalink": "https://reddit.com/r/ryobi/comments/1noifs6/ride_on_mower_battery_dying_want_to_make_sure_i/",
        "demand_signals": [
          "alternative"
        ],
        "matched_keywords": [
          "battery",
          "brushless"
        ]
      }
    ],
    "content_angle": "Lawn Equipment Reviews & Tips",
    "example_videos": [
      "Mower buying guide",
      "Lawn care mistakes to avoid"
    ],
    "hashtags": [
      "#lawncare",
      "#mower",
      "#landscaping",
      "#yardwork"
    ],
    "matched_videos": [
      {
        "video_id": "YkFqrESU39g",
        "title": "Gas Powered Leaf Blower or Battery Powered Leaf Blower? Which One Is Better? | eReplacementParts.com",
        "channel": "fixtechguides",
        "description_snippet": "We're back this week with another buyer's guide! We've taken you through Gas Powered vs Battery Powered Lawn Mowers (https://www.youtube.com/watch?v=FVhkavCI7h4) and Chainsaws (https://www.youtube....",
        "relevance_score": 80,
        "match_reasons": [
          "Theme keyword: lawn mower",
          "Theme keyword: mower",
          "Fuzzy theme keyword match: grass (75.0)",
          "Theme keyword: lawn",
          "Fuzzy theme keyword match: weed eater (70.0)",
          "Theme keyword: leaf blower",
          "Theme keyword: blower",
          "Product match: battery",
          "Reddit keyword: battery",
          "Content type: guide"
        ]
      },
      {
        "video_id": "0A2xOvuOYF4",
        "title": "Spring Engine Startup: Get Your Outdoor Power Equipment Ready for the Season | eReplacementParts.com",
        "channel": "fixtechguides",
        "description_snippet": "Whether you're looking at a Lawn Mower, Chainsaw, Leaf Blower or Trimmer, it's important to take the proper steps to get them started up every spring. Knowing the right way to deal with old...",
        "relevance_score": 60,
        "match_reasons": [
          "Theme keyword: lawn mower",
          "Theme keyword: mower",
          "Theme keyword: lawn",
          "Theme keyword: trimmer",
          "Theme keyword: leaf blower",
          "Theme keyword: blower"
        ]
      },
      {
        "video_id": "U4ppmcUWAAM",
        "title": "How to Sharpen the Blade on your Lawn Mower--A Quick Fix",
        "channel": "fixtechguides",
        "description_snippet": "Is your lawn mower starting to lose its cutting edge against even the smallest blades of grass? Well then it's time to follow this tutorial on how to sharpen your lawnmower blade.\n\nHelpful...",
        "relevance_score": 59,
        "match_reasons": [
          "Theme keyword: lawn mower",
          "Theme keyword: mower",
          "Theme keyword: grass",
          "Theme keyword: lawn",
          "Fuzzy theme keyword match: edger (80.0)",
          "Product match: blade",
          "Reddit keyword: blade"
        ]
      }
    ]
  },
  {
    "theme": "budget_options",
    "post_count": 3,
    "avg_engagement": 56.333333333333336,
    "total_comments": 143,
    "demand_strength": 169.0,
    "sample_posts": [
      {
        "subreddit": "BudgetFood",
        "title": "Some of my recent budget meals",
        "selftext": "Honey garlic glazed chicken thigh. Around $6.40 for 10 chicken thighs. Garlic glaze used about 3$ worth of marinade ingredients (soy, sesame oil, jarlic, honey, apple cider vinegar, free harvested green onion); 1.5 cups of marinade for all the thighs. Bought yakisoba for $4.50 and added fresh vegetables (onion, celery, carrots, brussel sprouts, free harvested swiss chard leaves). Free harvested summer squash with parmesean. Overall it balanced out to about $4-$5 per serving.\n\n[TANGENT] I was for",
        "score": 137,
        "num_comments": 14,
        "created_utc": 1758255730.0,
        "url": "https://www.reddit.com/gallery/1nktx19",
        "permalink": "https://reddit.com/r/budgetfood/comments/1nktx19/some_of_my_recent_budget_meals/",
        "demand_signals": [
          "budget",
          "expensive",
          "cheap",
          "expensive"
        ],
        "matched_keywords": [
          "chuck",
          "oven"
        ]
      },
      {
        "subreddit": "cookingforbeginners",
        "title": "Easiest things to do with potatoes?",
        "selftext": "Potatoes are extremely cheap where I am so i bought a 10lb bag and I'm looking for things to do with them. Normally I just cut them into fries and air fry them and while that's fine, I'm looking for something else I can do. Preferably minimal prep and either air fryer or instant pot-able.",
        "score": 30,
        "num_comments": 125,
        "created_utc": 1758731968.0,
        "url": "https://www.reddit.com/r/cookingforbeginners/comments/1nph3mo/easiest_things_to_do_with_potatoes/",
        "permalink": "https://reddit.com/r/cookingforbeginners/comments/1nph3mo/easiest_things_to_do_with_potatoes/",
        "demand_signals": [
          "cheap"
        ],
        "matched_keywords": [
          "air fryer",
          "instant pot"
        ]
      },
      {
        "subreddit": "AskEngineers",
        "title": "3D printing for industrial cycloidal gearbox",
        "selftext": "Hi everyone, so I am building a 6dof robot arm from scratch using aluminium and some 3d printed parts. I will use cycloidal gearboxes on all of the joints to increase the torque and precision. I have a small 3 axis cnc machine on which i will make the components.\n\nI have a very limited budget for the robot, so to spend less on bigger motors and raw aluminium i decided to make the outer housing of the cycloidal gearbox from petg or abs. Only the outside will be 3d printed along the motor covers a",
        "score": 2,
        "num_comments": 4,
        "created_utc": 1758648658.0,
        "url": "https://www.reddit.com/r/AskEngineers/comments/1nonr31/3d_printing_for_industrial_cycloidal_gearbox/",
        "permalink": "https://reddit.com/r/AskEngineers/comments/1nonr31/3d_printing_for_industrial_cycloidal_gearbox/",
        "demand_signals": [
          "budget"
        ],
        "matched_keywords": [
          "torque"
        ]
      }
    ],
    "content_angle": "Budget Tool & Appliance Reviews",
    "example_videos": [
      "Best budget power tools",
      "Cheap vs expensive tool comparison"
    ],
    "hashtags": [
      "#budgettools",
      "#affordabletools",
      "#tooldeals",
      "#budgetDIY"
    ],
    "matched_videos": [
      {
        "video_id": "xr1vf-sK_h8",
        "title": "How to Replace the Check Valve on an Air Compressor",
        "channel": "fixtechguides",
        "description_snippet": "REFRESH COMPRESSION: If leaking seals and service bills are compressing your expenses, it's time to face the fix. This tutorial will show you how to remove and install a new check valve on...",
        "relevance_score": 40,
        "match_reasons": [
          "Fuzzy theme keyword match: value (80.0)",
          "Fuzzy theme keyword match: deal (75.0)",
          "Fuzzy theme keyword match: sale (75.0)",
          "Fuzzy theme keyword match: price (80.0)",
          "Fuzzy Reddit keyword: chuck (80.0)",
          "Fuzzy Reddit keyword: oven (75.0)"
        ]
      },
      {
        "video_id": "dZ7CDNt7aQ4",
        "title": "DRYER REPAIR: How to Remove the Inlet Valve on Your Dryer | FIX.com",
        "channel": "fixtechguides",
        "description_snippet": "Dryers that utilize steam in their cycle need to have access to water, and the inlet valve allows that water to enter the dryer. If the valve is faulty you may experience issues with the steam...",
        "relevance_score": 36,
        "match_reasons": [
          "Fuzzy theme keyword match: value (80.0)",
          "Fuzzy theme keyword match: deal (75.0)",
          "Fuzzy theme keyword match: sale (75.0)",
          "Fuzzy theme keyword match: price (80.0)",
          "Fuzzy Reddit keyword: oven (75.0)"
        ]
      },
      {
        "video_id": "lmt2B0xH2t8",
        "title": "DRYER REPAIR: How to Install the Inlet Valve on Your Dryer | FIX.com",
        "channel": "fixtechguides",
        "description_snippet": "Dryers that use steam in their cycle need to have access to water, and the inlet valve allows that water to enter the dryer. If the valve is faulty you may experience issues with the steam...",
        "relevance_score": 36,
        "match_reasons": [
          "Fuzzy theme keyword match: value (80.0)",
          "Fuzzy theme keyword match: deal (75.0)",
          "Fuzzy theme keyword match: sale (75.0)",
          "Fuzzy theme keyword match: price (80.0)",
          "Fuzzy Reddit keyword: oven (75.0)"
        ]
      }
    ]
  }
]